LICENSE
MANIFEST.in
README.md
examples.txt
requirements.txt
setup.py
romme/__init__.py
romme/conversion.py
romme/dates.py
romme/names.py
romme/parse.py
romme/romans.py
romme.egg-info/PKG-INFO
romme.egg-info/SOURCES.txt
romme.egg-info/dependency_links.txt
romme.egg-info/requires.txt
romme.egg-info/top_level.txt