Metadata-Version: 1.1
Name: romme
Version: 0.1.0
Summary: Convert to/from French Republican calendar
Home-page: https://github.com/bfontaine/romme
Author: Baptiste Fontaine
Author-email: b@ptistefontaine.fr
License: Copyright © 2017 – Baptiste Fontaine
